autotwin_pnglib.py
autotwin_pnglib-0.1.2.dist-info/LICENSE
autotwin_pnglib-0.1.2.dist-info/METADATA
autotwin_pnglib-0.1.2.dist-info/WHEEL
autotwin_pnglib-0.1.2.dist-info/RECORD
