Metadata-Version: 2.1
Name: autotwin_pnglib
Version: 0.1.2
Summary: Petri Net Model Generation Library for Auto-Twin
License: BSD-3-Clause
Keywords: auto-twin,system discovery,Petri net
Author: Wei Cheng
Author-email: wei.cheng.me@gmail.com
Requires-Python: >=3.10,<4.0
Classifier: Development Status :: 1 - Planning
Classifier: Intended Audience :: Manufacturing
Classifier: License :: OSI Approved :: BSD License
Classifier: Operating System :: OS Independent
Classifier: Programming Language :: Python :: 3
Classifier: Programming Language :: Python :: 3.10
Classifier: Programming Language :: Python :: 3.11
Classifier: Programming Language :: Python :: 3.12
Classifier: Programming Language :: Python :: 3 :: Only
Requires-Dist: PySCIPOpt (>=5.1.1,<6.0.0)
Requires-Dist: SNAKES (>=0.9.33,<0.10.0)
Requires-Dist: autotwin_gmglib (>=0.1.4,<0.2.0)
Requires-Dist: matplotlib (>=3.8.3,<4.0.0)
Requires-Dist: neo4j (>=5.17.0,<6.0.0)
Requires-Dist: networkx (>=3.2.1,<4.0.0)
Requires-Dist: numpy (>=1.26.4,<2.0.0)
Requires-Dist: pandas (>=2.2.1,<3.0.0)
Requires-Dist: pygraphviz (>=1.12,<2.0)
Requires-Dist: scipy (>=1.13.0,<2.0.0)
